vast_api/__init__.py
vast_api/main.py
vast_api/util.py
vast_api/vast_ai.py
vast_api-1.0.0.dist-info/LICENSE
vast_api-1.0.0.dist-info/METADATA
vast_api-1.0.0.dist-info/WHEEL
vast_api-1.0.0.dist-info/RECORD
